sedsed.py
sedsed-2.0.0.dist-info/LICENSE
sedsed-2.0.0.dist-info/METADATA
sedsed-2.0.0.dist-info/WHEEL
sedsed-2.0.0.dist-info/entry_points.txt
sedsed-2.0.0.dist-info/top_level.txt
sedsed-2.0.0.dist-info/RECORD
