Metadata-Version: 2.1
Name: sedsed
Version: 2.0.0
Summary: Debugger and code formatter for sed scripts
Home-page: https://aurelio.net/projects/sedsed/
Author: Aurelio Jargas
Author-email: aurelio@aurelio.net
License: GPLv3
Project-URL: Bug Tracker, https://github.com/aureliojargas/sedsed/issues
Project-URL: Source Code, https://github.com/aureliojargas/sedsed
Platform: UNKNOWN
Classifier: Development Status :: 5 - Production/Stable
Classifier: Environment :: Console
Classifier: Intended Audience :: Developers
Classifier: License :: OSI Approved :: GNU General Public License v3 (GPLv3)
Classifier: Operating System :: OS Independent
Classifier: Programming Language :: Python :: 2
Classifier: Programming Language :: Python :: 2.7
Classifier: Programming Language :: Python :: 3
Classifier: Programming Language :: Python :: 3.4
Classifier: Programming Language :: Python :: 3.5
Classifier: Programming Language :: Python :: 3.6
Classifier: Programming Language :: Python :: 3.7
Classifier: Programming Language :: Python :: 3.8
Classifier: Programming Language :: Python
Classifier: Topic :: Software Development
Requires-Python: >=2.7, !=3.0.*, !=3.1.*, !=3.2.*, !=3.3.*
Requires-Dist: sedparse (==0.1.*)
